setup.py
distributions_ana/Binomialdistribution.py
distributions_ana/Gaussiandistribution.py
distributions_ana/Generaldistribution.py
distributions_ana/__init__.py
distributions_ana.egg-info/PKG-INFO
distributions_ana.egg-info/SOURCES.txt
distributions_ana.egg-info/dependency_links.txt
distributions_ana.egg-info/not-zip-safe
distributions_ana.egg-info/top_level.txt