Metadata-Version: 1.0
Name: distributions-ana
Version: 0.1
Summary: Gaussian and binomial distributions
Home-page: UNKNOWN
Author: Ananth
Author-email: UNKNOWN
License: UNKNOWN
Platform: UNKNOWN
